{"adult":false,"backdrop_path":"/ivtqSfKW3JFDdnbBf9BRCL9ngLQ.jpg","belongs_to_collection":{"id":9485,"name":"The Fast and the Furious Collection","poster_path":"/zF0FyC5GWBl7CEn3MV8jvpCMMbn.jpg","backdrop_path":"/pRxz33WtDEZm6KXNFNNa2amaVZY.jpg"},"budget":85000000,"genres":[{"id":28,"name":"Action"},{"id":80,"name":"Crime"},{"id":18,"name":"Drama"},{"id":53,"name":"Thriller"}],"homepage":"http://www.fastandfuriousmovie.net","id":13804,"imdb_id":"tt1013752","original_title":"Fast & Furious","overview":"When a crime brings them back to L.A., fugitive ex-con Dom Toretto reignites his feud with agent Brian O'Conner. But as they are forced to confront a shared enemy, Dom and Brian must give in to an uncertain new trust if they hope to outmaneuver him. And the two men will find the best way to get revenge: push the limits of what's possible behind the wheel.","popularity":10.1904398431127,"poster_path":"/ft8IqAGFs3V7i87z0t0EVRUjK1p.jpg","production_companies":[{"name":"Universal Pictures","id":33},{"name":"Original Film","id":333},{"name":"One Race Productions","id":1225},{"name":"Neal H. Moritz Productions","id":2882}],"production_countries":[{"iso_3166_1":"US","name":"United States of America"}],"release_date":"2009-04-03","revenue":363164265,"runtime":107,"spoken_languages":[{"iso_639_1":"en","name":"English"}],"status":"Released","tagline":"New Model. Original Parts.","title":"Fast & Furious","vote_average":6.2,"vote_count":900}